{
    "requestedYear":  2026,
    "generatedUtc":  "2026-03-22T11:17:32Z",
    "source":  "ProdIP.asn.stp_WebSite_NewAddedASNs",
    "items":  [
                  {
                      "autonomousSystem":  "AS142169",
                      "id":  142169,
                      "name":  "Hirdhav Technologies",
                      "type":  "Business",
                      "webSite":  "hirdhav.com",
                      "ipv4":  256,
                      "created":  "2026/01/01",
                      "lastUpdated":  "2026/01/01",
                      "country":  "Republic of India",
                      "rir":  "apnic",
                      "issues":  "stubas"
                  },
                  {
                      "autonomousSystem":  "AS142170",
                      "id":  142170,
                      "name":  "Satu Data Indonesia",
                      "type":  "ISP",
                      "webSite":  "1dataid.id",
                      "ipv4":  256,
                      "created":  "2026/01/02",
                      "lastUpdated":  "2026/01/02",
                      "country":  "Republic of Indonesia",
                      "rir":  "apnic",
                      "issues":  "stubas"
                  },
                  {
                      "autonomousSystem":  "AS142171",
                      "id":  142171,
                      "name":  "Yayasan (Syifa Al Khoeriyyah)",
                      "type":  "Business",
                      "webSite":  "alshifacharity.com",
                      "ipv4":  256,
                      "created":  "2026/01/02",
                      "lastUpdated":  "2026/01/02",
                      "country":  "Republic of Indonesia",
                      "rir":  "apnic",
                      "issues":  "stubas\\"
                  },
                  {
                      "autonomousSystem":  "AS274290",
                      "id":  274290,
                      "name":  "Yeya Wifil",
                      "type":  "ISP",
                      "webSite":  "yeyawifi.com",
                      "ipv4":  256,
                      "created":  "2026/01/02",
                      "lastUpdated":  "2026/01/03",
                      "country":  "Dominican Republic",
                      "rir":  "lacnic",
                      "issues":  "stubas\\bittorent"
                  },
                  {
                      "autonomousSystem":  "AS142176",
                      "id":  142176,
                      "name":  "Ziago Technologies",
                      "type":  "Hosting",
                      "webSite":  "ziagotechnologies.com",
                      "ipv4":  512,
                      "created":  "2026/01/05",
                      "lastUpdated":  "2026/01/05",
                      "country":  "Republic of India",
                      "rir":  "apnic",
                      "issues":  "stubas"
                  },
                  {
                      "autonomousSystem":  "AS142177",
                      "id":  142177,
                      "name":  "Deatras Network and Data Solution",
                      "type":  "ISP",
                      "webSite":  "deatrasnetwork.com",
                      "ipv4":  256,
                      "created":  "2026/01/05",
                      "lastUpdated":  "2026/01/05",
                      "country":  "Republic of the Philippines",
                      "rir":  "apnic",
                      "issues":  "none"
                  },
                  {
                      "autonomousSystem":  "AS142179",
                      "id":  142179,
                      "name":  "Indus Cloud",
                      "type":  "Hosting",
                      "webSite":  "indus-cloud.com",
                      "ipv4":  512,
                      "created":  "2026/01/07",
                      "lastUpdated":  "2026/01/07",
                      "country":  "Islamic Republic of Pakistan",
                      "rir":  "apnic",
                      "issues":  "none"
                  },
                  {
                      "autonomousSystem":  "AS142183",
                      "id":  142183,
                      "name":  "Juragan Multimedia Global",
                      "type":  "ISP",
                      "webSite":  "juraganmultimediaglobal.com",
                      "ipv4":  512,
                      "created":  "2026/01/08",
                      "lastUpdated":  "2026/01/08",
                      "country":  "Republic of Indonesia",
                      "rir":  "apnic",
                      "issues":  "stubas"
                  },
                  {
                      "autonomousSystem":  "AS142187",
                      "id":  142187,
                      "name":  "Protectiv IT Security",
                      "type":  "ISP",
                      "webSite":  "protectiv.ph",
                      "ipv4":  256,
                      "created":  "2026/01/08",
                      "lastUpdated":  "2026/01/13",
                      "country":  "Republic of the Philippines",
                      "rir":  "apnic",
                      "issues":  "none"
                  },
                  {
                      "autonomousSystem":  "AS142188",
                      "id":  142188,
                      "name":  "Aryaka Lintas Media",
                      "type":  "Hosting",
                      "webSite":  "aryakanet.com",
                      "ipv4":  256,
                      "created":  "2026/01/08",
                      "lastUpdated":  "2026/01/08",
                      "country":  "Republic of Indonesia",
                      "rir":  "apnic",
                      "issues":  "none"
                  },
                  {
                      "autonomousSystem":  "AS142189",
                      "id":  142189,
                      "name":  "Teja Bala Abadi",
                      "type":  "Business",
                      "webSite":  "teja.web.id",
                      "ipv4":  256,
                      "created":  "2026/01/08",
                      "lastUpdated":  "2026/01/08",
                      "country":  "Republic of Indonesia",
                      "rir":  "apnic",
                      "issues":  "stubas\\"
                  },
                  {
                      "autonomousSystem":  "AS142192",
                      "id":  142192,
                      "name":  "RRRL NET",
                      "type":  "ISP",
                      "webSite":  "rrrlnet.com",
                      "ipv4":  1536,
                      "created":  "2026/01/08",
                      "lastUpdated":  "2026/01/12",
                      "country":  "Bangladesh",
                      "rir":  "apnic",
                      "issues":  "stubas"
                  },
                  {
                      "autonomousSystem":  "AS202485",
                      "id":  202485,
                      "name":  "Mathias Giovanni Spadaro (NubiSystem)",
                      "type":  "Hosting",
                      "webSite":  "toptrees.online",
                      "ipv4":  256,
                      "created":  "2026/01/08",
                      "lastUpdated":  "2026/01/08",
                      "country":  "Italian Republic",
                      "rir":  "ripe",
                      "issues":  "stubas"
                  },
                  {
                      "autonomousSystem":  "AS274294",
                      "id":  274294,
                      "name":  "Cable Vision Mages",
                      "type":  "ISP",
                      "webSite":  "cablevisionmajes.pe",
                      "ipv4":  256,
                      "created":  "2026/01/09",
                      "lastUpdated":  "2026/01/10",
                      "country":  "Republic of Peru",
                      "rir":  "lacnic",
                      "issues":  "none"
                  },
                  {
                      "autonomousSystem":  "AS142193",
                      "id":  142193,
                      "name":  "Turbo Network Indonesia",
                      "type":  "ISP",
                      "webSite":  "turbonet.id",
                      "ipv4":  256,
                      "created":  "2026/01/09",
                      "lastUpdated":  "2026/01/12",
                      "country":  "Republic of Indonesia",
                      "rir":  "apnic",
                      "issues":  "stubas\\"
                  },
                  {
                      "autonomousSystem":  "AS142198",
                      "id":  142198,
                      "name":  "Giradz Media Nuzantrha",
                      "type":  "ISP",
                      "webSite":  "gmnetworks.id",
                      "ipv4":  512,
                      "created":  "2026/01/12",
                      "lastUpdated":  "2026/01/12",
                      "country":  "Republic of Indonesia",
                      "rir":  "apnic",
                      "issues":  "stubas\\"
                  },
                  {
                      "autonomousSystem":  "AS142200",
                      "id":  142200,
                      "name":  "Netnova",
                      "type":  "Business",
                      "webSite":  "netnova.global",
                      "ipv4":  512,
                      "created":  "2026/01/13",
                      "lastUpdated":  "2026/01/13",
                      "country":  "Hong Kong Special Administrative Region",
                      "rir":  "apnic",
                      "issues":  "stubas"
                  },
                  {
                      "autonomousSystem":  "AS142201",
                      "id":  142201,
                      "name":  "Axindo Infinitas Network",
                      "type":  "ISP",
                      "webSite":  "axindo-network.id",
                      "ipv4":  512,
                      "created":  "2026/01/13",
                      "lastUpdated":  "2026/01/13",
                      "country":  "Republic of Indonesia",
                      "rir":  "apnic",
                      "issues":  "none"
                  },
                  {
                      "autonomousSystem":  "AS142205",
                      "id":  142205,
                      "name":  "NetOz",
                      "type":  "Business",
                      "webSite":  "netoz.au",
                      "ipv4":  512,
                      "created":  "2026/01/14",
                      "lastUpdated":  "2026/01/17",
                      "country":  "Commonwealth of Australia",
                      "rir":  "apnic",
                      "issues":  "stubas"
                  },
                  {
                      "autonomousSystem":  "AS142207",
                      "id":  142207,
                      "name":  "WJY (Shanghai) Technology",
                      "type":  "Business",
                      "webSite":  "wjy.me",
                      "ipv4":  512,
                      "created":  "2026/01/14",
                      "lastUpdated":  "2026/01/14",
                      "country":  "People’s Republic of China",
                      "rir":  "apnic",
                      "issues":  "stubas"
                  },
                  {
                      "autonomousSystem":  "AS142210",
                      "id":  142210,
                      "name":  "GH Network and Cyber Cafe",
                      "type":  "Business",
                      "webSite":  "gh-network.net",
                      "ipv4":  256,
                      "created":  "2026/01/14",
                      "lastUpdated":  "2026/01/14",
                      "country":  "Bangladesh",
                      "rir":  "apnic",
                      "issues":  "stubas"
                  },
                  {
                      "autonomousSystem":  "AS402117",
                      "id":  402117,
                      "name":  "White Tie Productions",
                      "type":  "Business",
                      "webSite":  "whitetielive.com",
                      "ipv4":  256,
                      "created":  "2026/01/15",
                      "lastUpdated":  "2026/01/15",
                      "country":  "United States",
                      "rir":  "arin",
                      "issues":  "stubas"
                  },
                  {
                      "autonomousSystem":  "AS274298",
                      "id":  274298,
                      "name":  "Network Plus Peru",
                      "type":  "ISP",
                      "webSite":  "netplusperu.pe",
                      "ipv4":  256,
                      "created":  "2026/01/15",
                      "lastUpdated":  "2026/01/16",
                      "country":  "Republic of Peru",
                      "rir":  "lacnic",
                      "issues":  "stubas"
                  },
                  {
                      "autonomousSystem":  "AS275628",
                      "id":  275628,
                      "name":  "Meganet Telecomunicacoes",
                      "type":  "ISP",
                      "webSite":  "Not published",
                      "ipv4":  256,
                      "created":  "2026/01/15",
                      "lastUpdated":  "2026/01/15",
                      "country":  "Federative Republic of Brazil",
                      "rir":  "lacnic",
                      "issues":  "stubas"
                  },
                  {
                      "autonomousSystem":  "AS274302",
                      "id":  274302,
                      "name":  "Tecnowind",
                      "type":  "Hosting",
                      "webSite":  "dedicado.com.uy",
                      "ipv4":  512,
                      "created":  "2026/01/16",
                      "lastUpdated":  "2026/01/16",
                      "country":  "Oriental Republic of Uruguay",
                      "rir":  "lacnic",
                      "issues":  "none"
                  },
                  {
                      "autonomousSystem":  "AS402122",
                      "id":  402122,
                      "name":  "SSS.OOO",
                      "type":  "Hosting",
                      "webSite":  "sss.ooo",
                      "ipv4":  256,
                      "created":  "2026/01/16",
                      "lastUpdated":  "2026/01/16",
                      "country":  "United States",
                      "rir":  "arin",
                      "issues":  "stubas"
                  },
                  {
                      "autonomousSystem":  "AS142214",
                      "id":  142214,
                      "name":  "Fivestar Teknologi Nusantara",
                      "type":  "Business",
                      "webSite":  "fivestar.net.id",
                      "ipv4":  256,
                      "created":  "2026/01/19",
                      "lastUpdated":  "2026/01/19",
                      "country":  "Republic of Indonesia",
                      "rir":  "apnic",
                      "issues":  "stubas\\"
                  },
                  {
                      "autonomousSystem":  "AS142218",
                      "id":  142218,
                      "name":  "Sixty Four Networks",
                      "type":  "Hosting",
                      "webSite":  "Not published",
                      "ipv4":  256,
                      "created":  "2026/01/19",
                      "lastUpdated":  "2026/01/19",
                      "country":  "Bangladesh",
                      "rir":  "apnic",
                      "issues":  "stubas"
                  },
                  {
                      "autonomousSystem":  "AS142221",
                      "id":  142221,
                      "name":  "Fazznet Zetta Indonesia",
                      "type":  "ISP",
                      "webSite":  "fazznet.co.id",
                      "ipv4":  256,
                      "created":  "2026/01/20",
                      "lastUpdated":  "2026/01/20",
                      "country":  "Republic of Indonesia",
                      "rir":  "apnic",
                      "issues":  "none"
                  },
                  {
                      "autonomousSystem":  "AS402123",
                      "id":  402123,
                      "name":  "UNMTA",
                      "type":  "Hosting",
                      "webSite":  "unmta.net",
                      "ipv4":  256,
                      "created":  "2026/01/20",
                      "lastUpdated":  "2026/01/20",
                      "country":  "United States",
                      "rir":  "arin",
                      "issues":  "stubas\\"
                  },
                  {
                      "autonomousSystem":  "AS402127",
                      "id":  402127,
                      "name":  "Project Takoyaki Technologies",
                      "type":  "Business",
                      "webSite":  "takoyaki.io",
                      "ipv4":  256,
                      "created":  "2026/01/21",
                      "lastUpdated":  "2026/01/21",
                      "country":  "United States",
                      "rir":  "arin",
                      "issues":  "stubas"
                  },
                  {
                      "autonomousSystem":  "AS402130",
                      "id":  402130,
                      "name":  "Homemakers Upstate Group",
                      "type":  "Business",
                      "webSite":  "caregivershomecare.com",
                      "ipv4":  256,
                      "created":  "2026/01/21",
                      "lastUpdated":  "2026/01/21",
                      "country":  "United States",
                      "rir":  "arin",
                      "issues":  "stubas\\"
                  },
                  {
                      "autonomousSystem":  "AS142226",
                      "id":  142226,
                      "name":  "Dinas Komunikasi, Informatika, Statistik",
                      "type":  "ISP",
                      "webSite":  "kaimanakab.go.id",
                      "ipv4":  256,
                      "created":  "2026/01/21",
                      "lastUpdated":  "2026/01/22",
                      "country":  "Republic of Indonesia",
                      "rir":  "apnic",
                      "issues":  "stubas\\"
                  },
                  {
                      "autonomousSystem":  "AS142230",
                      "id":  142230,
                      "name":  "Bahari Nusantara Network",
                      "type":  "Business",
                      "webSite":  "baharinetwork.net",
                      "ipv4":  512,
                      "created":  "2026/01/22",
                      "lastUpdated":  "2026/01/22",
                      "country":  "Republic of Indonesia",
                      "rir":  "apnic",
                      "issues":  "none"
                  },
                  {
                      "autonomousSystem":  "AS142231",
                      "id":  142231,
                      "name":  "Institut Sains dan Teknologi Terpadu Surabaya",
                      "type":  "Business",
                      "webSite":  "istts.ac.id",
                      "ipv4":  256,
                      "created":  "2026/01/22",
                      "lastUpdated":  "2026/01/22",
                      "country":  "Republic of Indonesia",
                      "rir":  "apnic",
                      "issues":  "stubas\\"
                  },
                  {
                      "autonomousSystem":  "AS142232",
                      "id":  142232,
                      "name":  "Shamadhan Services",
                      "type":  "Business",
                      "webSite":  "shamadhan.com.bd",
                      "ipv4":  512,
                      "created":  "2026/01/22",
                      "lastUpdated":  "2026/01/22",
                      "country":  "Bangladesh",
                      "rir":  "apnic",
                      "issues":  "stubas"
                  },
                  {
                      "autonomousSystem":  "AS142238",
                      "id":  142238,
                      "name":  "Josu Global Teknologi",
                      "type":  "Hosting",
                      "webSite":  "jgt.co.id",
                      "ipv4":  256,
                      "created":  "2026/01/23",
                      "lastUpdated":  "2026/01/27",
                      "country":  "Republic of Indonesia",
                      "rir":  "apnic",
                      "issues":  "none"
                  },
                  {
                      "autonomousSystem":  "AS402143",
                      "id":  402143,
                      "name":  "PositionWatch",
                      "type":  "Business",
                      "webSite":  "positionwatch.com",
                      "ipv4":  512,
                      "created":  "2026/01/23",
                      "lastUpdated":  "2026/01/23",
                      "country":  "Canada",
                      "rir":  "arin",
                      "issues":  "none"
                  },
                  {
                      "autonomousSystem":  "AS402144",
                      "id":  402144,
                      "name":  "Networking West Virginia",
                      "type":  "Business",
                      "webSite":  "networkingwv.com",
                      "ipv4":  256,
                      "created":  "2026/01/26",
                      "lastUpdated":  "2026/01/26",
                      "country":  "United States",
                      "rir":  "arin",
                      "issues":  "stubas\\"
                  },
                  {
                      "autonomousSystem":  "AS402146",
                      "id":  402146,
                      "name":  "Bold Software",
                      "type":  "Business",
                      "webSite":  "bold.dev",
                      "ipv4":  256,
                      "created":  "2026/01/26",
                      "lastUpdated":  "2026/01/26",
                      "country":  "United States",
                      "rir":  "arin",
                      "issues":  "stubas"
                  },
                  {
                      "autonomousSystem":  "AS402153",
                      "id":  402153,
                      "name":  "Quick Tech Results",
                      "type":  "Hosting",
                      "webSite":  "quicktechresults.com",
                      "ipv4":  256,
                      "created":  "2026/01/27",
                      "lastUpdated":  "2026/01/27",
                      "country":  "United States",
                      "rir":  "arin",
                      "issues":  "none"
                  },
                  {
                      "autonomousSystem":  "AS142243",
                      "id":  142243,
                      "name":  "Asuransi Jiwa IFG",
                      "type":  "Hosting",
                      "webSite":  "ifg-life.id",
                      "ipv4":  256,
                      "created":  "2026/01/27",
                      "lastUpdated":  "2026/01/27",
                      "country":  "Republic of Indonesia",
                      "rir":  "apnic",
                      "issues":  "stubas"
                  },
                  {
                      "autonomousSystem":  "AS142244",
                      "id":  142244,
                      "name":  "Iotamine Cloud",
                      "type":  "Hosting",
                      "webSite":  "iotamine.com",
                      "ipv4":  256,
                      "created":  "2026/01/27",
                      "lastUpdated":  "2026/02/04",
                      "country":  "Republic of India",
                      "rir":  "apnic",
                      "issues":  "stubas\\"
                  },
                  {
                      "autonomousSystem":  "AS142245",
                      "id":  142245,
                      "name":  "Kastle (Fiji)",
                      "type":  "ISP",
                      "webSite":  "kastel.com.au",
                      "ipv4":  256,
                      "created":  "2026/01/27",
                      "lastUpdated":  "2026/01/27",
                      "country":  "Republic of Fiji",
                      "rir":  "apnic",
                      "issues":  "stubas"
                  },
                  {
                      "autonomousSystem":  "AS402157",
                      "id":  402157,
                      "name":  "Puppygirl Labs",
                      "type":  "Business",
                      "webSite":  "puppygirl.io",
                      "ipv4":  256,
                      "created":  "2026/01/28",
                      "lastUpdated":  "2026/01/28",
                      "country":  "United States",
                      "rir":  "arin",
                      "issues":  "stubas"
                  },
                  {
                      "autonomousSystem":  "AS402158",
                      "id":  402158,
                      "name":  "CyberForest",
                      "type":  "Hosting",
                      "webSite":  "bbkhost.com",
                      "ipv4":  256,
                      "created":  "2026/01/28",
                      "lastUpdated":  "2026/02/06",
                      "country":  "United States",
                      "rir":  "arin",
                      "issues":  "stubas"
                  },
                  {
                      "autonomousSystem":  "AS402162",
                      "id":  402162,
                      "name":  "Benthost",
                      "type":  "Hosting",
                      "webSite":  "shieldmanagement.com",
                      "ipv4":  768,
                      "created":  "2026/01/29",
                      "lastUpdated":  "2026/01/29",
                      "country":  "United States",
                      "rir":  "arin",
                      "issues":  "none"
                  },
                  {
                      "autonomousSystem":  "AS402163",
                      "id":  402163,
                      "name":  "SkyVault AI",
                      "type":  "Business",
                      "webSite":  "skyv.ai",
                      "ipv4":  256,
                      "created":  "2026/01/29",
                      "lastUpdated":  "2026/01/29",
                      "country":  "United States",
                      "rir":  "arin",
                      "issues":  "stubas\\"
                  },
                  {
                      "autonomousSystem":  "AS142252",
                      "id":  142252,
                      "name":  "T Dot Net",
                      "type":  "ISP",
                      "webSite":  "tdotnetbd.com",
                      "ipv4":  256,
                      "created":  "2026/01/29",
                      "lastUpdated":  "2026/01/29",
                      "country":  "Bangladesh",
                      "rir":  "apnic",
                      "issues":  "stubas"
                  },
                  {
                      "autonomousSystem":  "AS142253",
                      "id":  142253,
                      "name":  "Ebliss Info Systems",
                      "type":  "ISP",
                      "webSite":  "eblissinfosys.com",
                      "ipv4":  512,
                      "created":  "2026/01/29",
                      "lastUpdated":  "2026/01/29",
                      "country":  "Republic of India",
                      "rir":  "apnic",
                      "issues":  "none"
                  },
                  {
                      "autonomousSystem":  "AS402164",
                      "id":  402164,
                      "name":  "Rofael Aleezada",
                      "type":  "Business",
                      "webSite":  "rofael.net",
                      "ipv4":  256,
                      "created":  "2026/01/30",
                      "lastUpdated":  "2026/02/13",
                      "country":  "United States",
                      "rir":  "arin",
                      "issues":  "none"
                  },
                  {
                      "autonomousSystem":  "AS142257",
                      "id":  142257,
                      "name":  "Kevin Cahaya Nusantara",
                      "type":  "Business",
                      "webSite":  "kevincahaya.id",
                      "ipv4":  256,
                      "created":  "2026/02/02",
                      "lastUpdated":  "2026/02/02",
                      "country":  "Republic of Indonesia",
                      "rir":  "apnic",
                      "issues":  "none"
                  },
                  {
                      "autonomousSystem":  "AS142258",
                      "id":  142258,
                      "name":  "Pesona Network Mediautama",
                      "type":  "Business",
                      "webSite":  "pesonamedia.net",
                      "ipv4":  512,
                      "created":  "2026/02/02",
                      "lastUpdated":  "2026/02/02",
                      "country":  "Republic of Indonesia",
                      "rir":  "apnic",
                      "issues":  "stubas\\"
                  },
                  {
                      "autonomousSystem":  "AS142259",
                      "id":  142259,
                      "name":  "92Host",
                      "type":  "ISP",
                      "webSite":  "92host.com",
                      "ipv4":  512,
                      "created":  "2026/02/02",
                      "lastUpdated":  "2026/02/02",
                      "country":  "Hong Kong Special Administrative Region",
                      "rir":  "apnic",
                      "issues":  "stubas\\bittorent"
                  },
                  {
                      "autonomousSystem":  "AS142264",
                      "id":  142264,
                      "name":  "Sky Base Technology Digital",
                      "type":  "ISP",
                      "webSite":  "btd.co.id",
                      "ipv4":  256,
                      "created":  "2026/02/03",
                      "lastUpdated":  "2026/02/05",
                      "country":  "Republic of Indonesia",
                      "rir":  "apnic",
                      "issues":  "stubas"
                  },
                  {
                      "autonomousSystem":  "AS274311",
                      "id":  274311,
                      "name":  "Interos - Internet Service",
                      "type":  "Hosting",
                      "webSite":  "interos.com.co",
                      "ipv4":  256,
                      "created":  "2026/02/03",
                      "lastUpdated":  "2026/02/04",
                      "country":  "Republic of Colombia",
                      "rir":  "lacnic",
                      "issues":  "none"
                  },
                  {
                      "autonomousSystem":  "AS142265",
                      "id":  142265,
                      "name":  "Digital o2",
                      "type":  "Business",
                      "webSite":  "digitalo2.com.au",
                      "ipv4":  512,
                      "created":  "2026/02/04",
                      "lastUpdated":  "2026/02/04",
                      "country":  "Commonwealth of Australia",
                      "rir":  "apnic",
                      "issues":  "stubas"
                  },
                  {
                      "autonomousSystem":  "AS402180",
                      "id":  402180,
                      "name":  "Applied Technology Group",
                      "type":  "ISP",
                      "webSite":  "atg-inc.com",
                      "ipv4":  512,
                      "created":  "2026/02/05",
                      "lastUpdated":  "2026/02/05",
                      "country":  "United States",
                      "rir":  "arin",
                      "issues":  "stubas\\bittorent"
                  },
                  {
                      "autonomousSystem":  "AS402184",
                      "id":  402184,
                      "name":  "One15",
                      "type":  "Inactive",
                      "webSite":  "one15.io",
                      "ipv4":  512,
                      "created":  "2026/02/05",
                      "lastUpdated":  "2026/02/05",
                      "country":  "United States",
                      "rir":  "arin",
                      "issues":  "stubas"
                  },
                  {
                      "autonomousSystem":  "AS154481",
                      "id":  154481,
                      "name":  "Tachileik Jade Dragon Company",
                      "type":  "ISP",
                      "webSite":  "tjdnetwork.com",
                      "ipv4":  512,
                      "created":  "2026/02/05",
                      "lastUpdated":  "2026/02/05",
                      "country":  "Union of Burma",
                      "rir":  "apnic",
                      "issues":  "none"
                  },
                  {
                      "autonomousSystem":  "AS154486",
                      "id":  154486,
                      "name":  "Rei Mimura",
                      "type":  "Hosting",
                      "webSite":  "lessismore.asia",
                      "ipv4":  256,
                      "created":  "2026/02/06",
                      "lastUpdated":  "2026/02/10",
                      "country":  "Japan",
                      "rir":  "apnic",
                      "issues":  "none"
                  },
                  {
                      "autonomousSystem":  "AS154489",
                      "id":  154489,
                      "name":  "Magnet Telecommunication",
                      "type":  "ISP",
                      "webSite":  "magnetbd.net",
                      "ipv4":  256,
                      "created":  "2026/02/06",
                      "lastUpdated":  "2026/02/06",
                      "country":  "Bangladesh",
                      "rir":  "apnic",
                      "issues":  "stubas"
                  },
                  {
                      "autonomousSystem":  "AS402186",
                      "id":  402186,
                      "name":  "SeroWeb",
                      "type":  "ISP",
                      "webSite":  "seroweb.xyz",
                      "ipv4":  4352,
                      "created":  "2026/02/06",
                      "lastUpdated":  "2026/02/06",
                      "country":  "United States",
                      "rir":  "arin",
                      "issues":  "none"
                  },
                  {
                      "autonomousSystem":  "AS402187",
                      "id":  402187,
                      "name":  "AANSys Network",
                      "type":  "Inactive",
                      "webSite":  "aansysnetwork.com",
                      "ipv4":  0,
                      "created":  "2026/02/06",
                      "lastUpdated":  "2026/02/06",
                      "country":  "United States",
                      "rir":  "arin",
                      "issues":  "none"
                  },
                  {
                      "autonomousSystem":  "AS402192",
                      "id":  402192,
                      "name":  "The Nova Telephone Company",
                      "type":  "ISP",
                      "webSite":  "kclenterprises.net",
                      "ipv4":  768,
                      "created":  "2026/02/09",
                      "lastUpdated":  "2026/02/09",
                      "country":  "United States",
                      "rir":  "arin",
                      "issues":  "stubas\\"
                  },
                  {
                      "autonomousSystem":  "AS402193",
                      "id":  402193,
                      "name":  "UInt8",
                      "type":  "Business",
                      "webSite":  "uint8.co",
                      "ipv4":  256,
                      "created":  "2026/02/09",
                      "lastUpdated":  "2026/02/09",
                      "country":  "United States",
                      "rir":  "arin",
                      "issues":  "none"
                  },
                  {
                      "autonomousSystem":  "AS402194",
                      "id":  402194,
                      "name":  "14097335 Canada",
                      "type":  "Business",
                      "webSite":  "bainmagique.com",
                      "ipv4":  256,
                      "created":  "2026/02/09",
                      "lastUpdated":  "2026/02/17",
                      "country":  "Canada",
                      "rir":  "arin",
                      "issues":  "stubas\\"
                  },
                  {
                      "autonomousSystem":  "AS402196",
                      "id":  402196,
                      "name":  "Ajax Networks",
                      "type":  "Hosting",
                      "webSite":  "ajaxnetworks.us",
                      "ipv4":  256,
                      "created":  "2026/02/09",
                      "lastUpdated":  "2026/02/09",
                      "country":  "United States",
                      "rir":  "arin",
                      "issues":  "none"
                  },
                  {
                      "autonomousSystem":  "AS402197",
                      "id":  402197,
                      "name":  "Residence Fiber",
                      "type":  "Business",
                      "webSite":  "residencefiber.com",
                      "ipv4":  768,
                      "created":  "2026/02/09",
                      "lastUpdated":  "2026/03/06",
                      "country":  "United States",
                      "rir":  "arin",
                      "issues":  "stubas\\"
                  },
                  {
                      "autonomousSystem":  "AS154491",
                      "id":  154491,
                      "name":  "Netcore Company",
                      "type":  "Business",
                      "webSite":  "netcore.com.vn",
                      "ipv4":  512,
                      "created":  "2026/02/09",
                      "lastUpdated":  "2026/02/09",
                      "country":  "Socialist Republic of Vietnam",
                      "rir":  "apnic",
                      "issues":  "stubas"
                  },
                  {
                      "autonomousSystem":  "AS154492",
                      "id":  154492,
                      "name":  "Protergo",
                      "type":  "ISP",
                      "webSite":  "protergo.id",
                      "ipv4":  256,
                      "created":  "2026/02/10",
                      "lastUpdated":  "2026/02/10",
                      "country":  "Republic of Indonesia",
                      "rir":  "apnic",
                      "issues":  "stubas"
                  },
                  {
                      "autonomousSystem":  "AS154499",
                      "id":  154499,
                      "name":  "Bobcard",
                      "type":  "Business",
                      "webSite":  "bobcard.co.in",
                      "ipv4":  256,
                      "created":  "2026/02/10",
                      "lastUpdated":  "2026/02/10",
                      "country":  "Republic of India",
                      "rir":  "apnic",
                      "issues":  "stubas"
                  },
                  {
                      "autonomousSystem":  "AS275647",
                      "id":  275647,
                      "name":  "Castilhos Provedor de Internet",
                      "type":  "Business",
                      "webSite":  "castilhonet.psi.br",
                      "ipv4":  256,
                      "created":  "2026/02/10",
                      "lastUpdated":  "2026/02/16",
                      "country":  "Federative Republic of Brazil",
                      "rir":  "lacnic",
                      "issues":  "bittorent"
                  },
                  {
                      "autonomousSystem":  "AS402203",
                      "id":  402203,
                      "name":  "RAC Network",
                      "type":  "Business",
                      "webSite":  "racnet.xyz",
                      "ipv4":  3072,
                      "created":  "2026/02/10",
                      "lastUpdated":  "2026/02/10",
                      "country":  "United States",
                      "rir":  "arin",
                      "issues":  "stubas\\"
                  },
                  {
                      "autonomousSystem":  "AS402210",
                      "id":  402210,
                      "name":  "LaChollaNet",
                      "type":  "Business",
                      "webSite":  "lachollanet.com",
                      "ipv4":  256,
                      "created":  "2026/02/11",
                      "lastUpdated":  "2026/02/11",
                      "country":  "United States",
                      "rir":  "arin",
                      "issues":  "none"
                  },
                  {
                      "autonomousSystem":  "AS154500",
                      "id":  154500,
                      "name":  "Digital Fiber Tech",
                      "type":  "Business",
                      "webSite":  "irinn.in",
                      "ipv4":  256,
                      "created":  "2026/02/11",
                      "lastUpdated":  "2026/02/11",
                      "country":  "Republic of India",
                      "rir":  "apnic",
                      "issues":  "stubas"
                  },
                  {
                      "autonomousSystem":  "AS154495",
                      "id":  154495,
                      "name":  "Sterlink Permata Indonesia",
                      "type":  "Business",
                      "webSite":  "sterlinknet.com",
                      "ipv4":  512,
                      "created":  "2026/02/11",
                      "lastUpdated":  "2026/02/11",
                      "country":  "Republic of Indonesia",
                      "rir":  "apnic",
                      "issues":  "stubas\\"
                  },
                  {
                      "autonomousSystem":  "AS154502",
                      "id":  154502,
                      "name":  "Land and Houses Bank Public Company",
                      "type":  "Business",
                      "webSite":  "lhbank.co.th",
                      "ipv4":  256,
                      "created":  "2026/02/12",
                      "lastUpdated":  "2026/02/12",
                      "country":  "Kingdom of Thailand",
                      "rir":  "apnic",
                      "issues":  "stubas"
                  },
                  {
                      "autonomousSystem":  "AS154503",
                      "id":  154503,
                      "name":  "Trimafa Computindo Networking",
                      "type":  "Business",
                      "webSite":  "trimafa.net.id",
                      "ipv4":  256,
                      "created":  "2026/02/12",
                      "lastUpdated":  "2026/02/18",
                      "country":  "Republic of Indonesia",
                      "rir":  "apnic",
                      "issues":  "stubas"
                  },
                  {
                      "autonomousSystem":  "AS154507",
                      "id":  154507,
                      "name":  "Nexaroot Technology India",
                      "type":  "Business",
                      "webSite":  "nexaroot.in",
                      "ipv4":  512,
                      "created":  "2026/02/12",
                      "lastUpdated":  "2026/02/12",
                      "country":  "Republic of India",
                      "rir":  "apnic",
                      "issues":  "stubas"
                  },
                  {
                      "autonomousSystem":  "AS154509",
                      "id":  154509,
                      "name":  "Langit Borneo Network",
                      "type":  "Business",
                      "webSite":  "langitborneonetwork.my.id",
                      "ipv4":  256,
                      "created":  "2026/02/13",
                      "lastUpdated":  "2026/02/18",
                      "country":  "Republic of Indonesia",
                      "rir":  "apnic",
                      "issues":  "stubas\\"
                  },
                  {
                      "autonomousSystem":  "AS154512",
                      "id":  154512,
                      "name":  "Toptus Broadband Services",
                      "type":  "ISP",
                      "webSite":  "irinn.in",
                      "ipv4":  256,
                      "created":  "2026/02/16",
                      "lastUpdated":  "2026/02/16",
                      "country":  "Republic of India",
                      "rir":  "apnic",
                      "issues":  "stubas"
                  },
                  {
                      "autonomousSystem":  "AS154514",
                      "id":  154514,
                      "name":  "M/S Mihad Enterprise",
                      "type":  "ISP",
                      "webSite":  "mihadnet.com",
                      "ipv4":  256,
                      "created":  "2026/02/16",
                      "lastUpdated":  "2026/02/22",
                      "country":  "Bangladesh",
                      "rir":  "apnic",
                      "issues":  "stubas"
                  },
                  {
                      "autonomousSystem":  "AS154516",
                      "id":  154516,
                      "name":  "Perfect Network",
                      "type":  "Business",
                      "webSite":  "perfect.my",
                      "ipv4":  512,
                      "created":  "2026/02/17",
                      "lastUpdated":  "2026/02/17",
                      "country":  "Malaysia",
                      "rir":  "apnic",
                      "issues":  "stubas"
                  },
                  {
                      "autonomousSystem":  "AS402212",
                      "id":  402212,
                      "name":  "Nicktronic IT",
                      "type":  "Business",
                      "webSite":  "nicktronic.com",
                      "ipv4":  256,
                      "created":  "2026/02/20",
                      "lastUpdated":  "2026/02/20",
                      "country":  "United States",
                      "rir":  "arin",
                      "issues":  "stubas"
                  },
                  {
                      "autonomousSystem":  "AS402213",
                      "id":  402213,
                      "name":  "Bills Stadium and Events Company",
                      "type":  "Business",
                      "webSite":  "nfl.net",
                      "ipv4":  256,
                      "created":  "2026/02/20",
                      "lastUpdated":  "2026/02/20",
                      "country":  "United States",
                      "rir":  "arin",
                      "issues":  "stubas\\"
                  },
                  {
                      "autonomousSystem":  "AS402214",
                      "id":  402214,
                      "name":  "Thinkillion",
                      "type":  "Business",
                      "webSite":  "thinkillion.xyz",
                      "ipv4":  512,
                      "created":  "2026/02/20",
                      "lastUpdated":  "2026/02/20",
                      "country":  "United States",
                      "rir":  "arin",
                      "issues":  "stubas\\"
                  },
                  {
                      "autonomousSystem":  "AS402221",
                      "id":  402221,
                      "name":  "Exaserver",
                      "type":  "Hosting",
                      "webSite":  "exaserver.cloud",
                      "ipv4":  512,
                      "created":  "2026/02/23",
                      "lastUpdated":  "2026/02/23",
                      "country":  "United States",
                      "rir":  "arin",
                      "issues":  "stubas\\"
                  },
                  {
                      "autonomousSystem":  "AS402226",
                      "id":  402226,
                      "name":  "OnlyScans",
                      "type":  "Hosting",
                      "webSite":  "onlyscans.net",
                      "ipv4":  256,
                      "created":  "2026/02/25",
                      "lastUpdated":  "2026/02/25",
                      "country":  "United States",
                      "rir":  "arin",
                      "issues":  "stubas\\"
                  },
                  {
                      "autonomousSystem":  "AS154401",
                      "id":  154401,
                      "name":  "Sahabat Internet Nusantara",
                      "type":  "ISP",
                      "webSite":  "snet.co.id",
                      "ipv4":  512,
                      "created":  "2026/02/25",
                      "lastUpdated":  "2026/02/25",
                      "country":  "Republic of Indonesia",
                      "rir":  "apnic",
                      "issues":  "stubas\\"
                  },
                  {
                      "autonomousSystem":  "AS154479",
                      "id":  154479,
                      "name":  "Panca Cita Synetrix",
                      "type":  "Business",
                      "webSite":  "synetrix.id",
                      "ipv4":  512,
                      "created":  "2026/02/25",
                      "lastUpdated":  "2026/02/25",
                      "country":  "Republic of Indonesia",
                      "rir":  "apnic",
                      "issues":  "none"
                  },
                  {
                      "autonomousSystem":  "AS402230",
                      "id":  402230,
                      "name":  "Strato Labs",
                      "type":  "Business",
                      "webSite":  "strato.do",
                      "ipv4":  256,
                      "created":  "2026/02/26",
                      "lastUpdated":  "2026/02/26",
                      "country":  "United States",
                      "rir":  "arin",
                      "issues":  "stubas\\"
                  },
                  {
                      "autonomousSystem":  "AS402234",
                      "id":  402234,
                      "name":  "Los Alisos Ranch Company",
                      "type":  "Business",
                      "webSite":  "losalisosranchco.com",
                      "ipv4":  512,
                      "created":  "2026/02/26",
                      "lastUpdated":  "2026/02/26",
                      "country":  "United States",
                      "rir":  "arin",
                      "issues":  "stubas\\"
                  },
                  {
                      "autonomousSystem":  "AS402236",
                      "id":  402236,
                      "name":  "Patriot Broadband",
                      "type":  "Hosting",
                      "webSite":  "patriot-broadband.com",
                      "ipv4":  1792,
                      "created":  "2026/02/26",
                      "lastUpdated":  "2026/02/26",
                      "country":  "United States",
                      "rir":  "arin",
                      "issues":  "stubas\\"
                  },
                  {
                      "autonomousSystem":  "AS154521",
                      "id":  154521,
                      "name":  "Digital Prima Solution",
                      "type":  "Business",
                      "webSite":  "digitalprima.id",
                      "ipv4":  256,
                      "created":  "2026/02/26",
                      "lastUpdated":  "2026/02/26",
                      "country":  "Republic of Indonesia",
                      "rir":  "apnic",
                      "issues":  "stubas"
                  },
                  {
                      "autonomousSystem":  "AS402247",
                      "id":  402247,
                      "name":  "Flew",
                      "type":  "Business",
                      "webSite":  "flew.network",
                      "ipv4":  256,
                      "created":  "2026/03/02",
                      "lastUpdated":  "2026/03/13",
                      "country":  "United States",
                      "rir":  "arin",
                      "issues":  "stubas\\"
                  },
                  {
                      "autonomousSystem":  "AS402259",
                      "id":  402259,
                      "name":  "ZT Enterprises",
                      "type":  "Business",
                      "webSite":  "lyx.ac",
                      "ipv4":  0,
                      "created":  "2026/03/06",
                      "lastUpdated":  "2026/03/06",
                      "country":  "United States",
                      "rir":  "arin",
                      "issues":  "stubas\\"
                  },
                  {
                      "autonomousSystem":  "AS142216",
                      "id":  142216,
                      "name":  "Tridata Network Indonesia",
                      "type":  "ISP",
                      "webSite":  "tridatanetwork.id",
                      "ipv4":  512,
                      "created":  "2026/03/09",
                      "lastUpdated":  "2026/03/09",
                      "country":  "Republic of Indonesia",
                      "rir":  "apnic",
                      "issues":  "none"
                  },
                  {
                      "autonomousSystem":  "AS402274",
                      "id":  402274,
                      "name":  "ZenNet",
                      "type":  "Business",
                      "webSite":  "zennet.co",
                      "ipv4":  0,
                      "created":  "2026/03/10",
                      "lastUpdated":  "2026/03/10",
                      "country":  "United States",
                      "rir":  "arin",
                      "issues":  "stubas\\"
                  },
                  {
                      "autonomousSystem":  "AS154480",
                      "id":  154480,
                      "name":  "Gerbang Nusantara Sakti",
                      "type":  "Business",
                      "webSite":  "gerbangnusantarasakti.net",
                      "ipv4":  256,
                      "created":  "2026/03/11",
                      "lastUpdated":  "2026/03/11",
                      "country":  "Republic of Indonesia",
                      "rir":  "apnic",
                      "issues":  "stubas\\"
                  },
                  {
                      "autonomousSystem":  "AS402287",
                      "id":  402287,
                      "name":  "PGAL",
                      "type":  null,
                      "webSite":  "pgal.com",
                      "ipv4":  256,
                      "created":  "2026/03/13",
                      "lastUpdated":  "2026/03/13",
                      "country":  "United States",
                      "rir":  "arin",
                      "issues":  "none"
                  },
                  {
                      "autonomousSystem":  "AS402298",
                      "id":  402298,
                      "name":  "HYW Global",
                      "type":  "Inactive",
                      "webSite":  "cxy.hk",
                      "ipv4":  0,
                      "created":  "2026/03/13",
                      "lastUpdated":  "2026/03/13",
                      "country":  "United States",
                      "rir":  "arin",
                      "issues":  "none"
                  }
              ]
}